comon/__init__.py
comon/api.py
comon/models.py
comon/utils.py
comon-0.1.0.dist-info/LICENSE
comon-0.1.0.dist-info/METADATA
comon-0.1.0.dist-info/WHEEL
comon-0.1.0.dist-info/top_level.txt
comon-0.1.0.dist-info/RECORD
