Metadata-Version: 2.1
Name: comon
Version: 0.1.0
License-File: LICENSE
Requires-Dist: requests
